LICENSE.md
README.md
pyproject.toml
src/querypool/__init__.py
src/querypool.egg-info/PKG-INFO
src/querypool.egg-info/SOURCES.txt
src/querypool.egg-info/dependency_links.txt
src/querypool.egg-info/requires.txt
src/querypool.egg-info/top_level.txt
src/querypool/pools/__init__.py
src/querypool/pools/gevent_cooperative.py
src/querypool/pools/gevent_noncooperative.py
src/querypool/pools/interface.py
src/querypool/pools/threading.py
src/querypool/tests/__init__.py
src/querypool/tests/test_maxsizedict.py
src/querypool/tests/test_pools.py
src/querypool/utils/__init__.py
src/querypool/utils/maxsizedict.py