Metadata-Version: 2.4
Name: querypool
Version: 1.1.0
Summary: Execution pool with caching and early return
Author-email: ESRF <dau-pydev@esrf.fr>
License: # MIT License
Project-URL: Homepage, https://gitlab.esrf.fr/dau/querypool/
Project-URL: Documentation, https://querypool.readthedocs.io/
Project-URL: Repository, https://gitlab.esrf.fr/dau/querypool/
Project-URL: Issues, https://gitlab.esrf.fr/dau/querypool/issues
Project-URL: Changelog, https://gitlab.esrf.fr/dau/querypool/-/blob/main/CHANGELOG.md
Classifier: Intended Audience :: Science/Research
Classifier: License :: OSI Approved :: MIT License
Classifier: Programming Language :: Python :: 3
Requires-Python: >=3.8
License-File: LICENSE.md
Provides-Extra: test
Requires-Dist: pytest>=7; extra == "test"
Requires-Dist: pytest-timeout>=2.1; extra == "test"
Provides-Extra: dev
Requires-Dist: querypool[test]; extra == "dev"
Requires-Dist: black>=25; extra == "dev"
Requires-Dist: flake8>=4; extra == "dev"
Provides-Extra: doc
Requires-Dist: querypool[test]; extra == "doc"
Requires-Dist: sphinx>=4.5; extra == "doc"
Requires-Dist: sphinx-autodoc-typehints>=1.16; extra == "doc"
Requires-Dist: pydata-sphinx-theme; extra == "doc"
Dynamic: license-file
